living_memory_dynamics-1.3.0.dist-info/licenses/LICENSE
lmd/__init__.py
lmd/chaos_monitor.py
lmd/config.py
lmd/coupling.py
lmd/creative_ideation.py
lmd/creative_leaps.py
lmd/curiosity_prober.py
lmd/dynamics.py
lmd/heartbeat_integration.py
lmd/hierarchical_ideas.py
lmd/ideation.py
lmd/imagination.py
lmd/language_grounding.py
lmd/living_memory.py
lmd/metabolism.py
lmd/narrative.py
lmd/plausibility.py
lmd/prediction.py
lmd/py.typed
lmd/safeguards.py
lmd/story_encoder.py
lmd/toy_system.py
lmd/cuda/__init__.py
lmd/cuda/batch_ops.py
lmd/cuda/fallback.py
lmd/cuda/kernels.py
living_memory_dynamics-1.3.0.dist-info/METADATA
living_memory_dynamics-1.3.0.dist-info/WHEEL
living_memory_dynamics-1.3.0.dist-info/top_level.txt
living_memory_dynamics-1.3.0.dist-info/RECORD
