Metadata-Version: 2.4
Name: living-memory-dynamics
Version: 1.3.0
Summary: Living Memory Dynamics - A Novel Framework for Narrative-Generating Episodic Memory with Creative Leaps and Language Grounding
Author-email: "Joshua R. Thomas" <mordiaky@gmail.com>
License: Living Memory Dynamics (LMD) License
Project-URL: Homepage, https://github.com/mordiaky/living-memory-dynamics
Project-URL: Documentation, https://github.com/mordiaky/living-memory-dynamics#readme
Project-URL: Repository, https://github.com/mordiaky/living-memory-dynamics
Project-URL: Issues, https://github.com/mordiaky/living-memory-dynamics/issues
Keywords: memory,episodic-memory,narrative,creative-ai,embedding,cognitive-architecture,neural-network,imagination,creativity
Classifier: Development Status :: 4 - Beta
Classifier: Intended Audience :: Science/Research
Classifier: Intended Audience :: Developers
Classifier: Topic :: Scientific/Engineering :: Artificial Intelligence
Classifier: Programming Language :: Python :: 3
Classifier: Programming Language :: Python :: 3.9
Classifier: Programming Language :: Python :: 3.10
Classifier: Programming Language :: Python :: 3.11
Classifier: Programming Language :: Python :: 3.12
Classifier: Operating System :: OS Independent
Requires-Python: >=3.9
License-File: LICENSE
Requires-Dist: torch>=2.0.0
Requires-Dist: numpy>=1.20.0
Provides-Extra: dev
Requires-Dist: pytest>=7.0.0; extra == "dev"
Requires-Dist: pytest-cov>=4.0.0; extra == "dev"
Requires-Dist: black>=23.0.0; extra == "dev"
Requires-Dist: ruff>=0.1.0; extra == "dev"
Requires-Dist: mypy>=1.0.0; extra == "dev"
Provides-Extra: cuda
Requires-Dist: triton>=2.0.0; extra == "cuda"
Provides-Extra: language
Requires-Dist: sentence-transformers>=2.2.0; extra == "language"
Provides-Extra: llm
Requires-Dist: ollama>=0.1.0; extra == "llm"
Requires-Dist: openai>=1.0.0; extra == "llm"
Provides-Extra: all
Requires-Dist: living-memory-dynamics[cuda,dev,language,llm]; extra == "all"
Dynamic: license-file
